LICENSE
MANIFEST.in
README.md
setup.py
src/ea_agents/__init__.py
src/ea_agents/plugins/__init__.py
src/ea_agents/plugins/selenium3/__init__.py
src/ea_agents/plugins/selenium3/agent_selenium.py
src/ea_agents/plugins/selenium3/bin/SELENIUM_VERSION
src/ea_agents/plugins/selenium3/bin/chromedriver.exe
src/ea_agents/plugins/selenium3/bin/geckodriver.exe
src/ea_agents/plugins/selenium3/bin/msedgedriver.exe
src/ea_agents/plugins/selenium3/bin/selenium-script.bat
src/ea_agents/plugins/selenium3/bin/selenium-server-standalone.jar
src/extensiveautomation_agent_plugin_selenium.egg-info/PKG-INFO
src/extensiveautomation_agent_plugin_selenium.egg-info/SOURCES.txt
src/extensiveautomation_agent_plugin_selenium.egg-info/dependency_links.txt
src/extensiveautomation_agent_plugin_selenium.egg-info/requires.txt
src/extensiveautomation_agent_plugin_selenium.egg-info/top_level.txt